INSTALL.rst
LICENSE
MANIFEST.in
README.rst
setup.cfg
setup.py
versioneer.py
berk/__init__.py
berk/_version.py
berk/archive.py
berk/jobs.py
berk/startup.py
berk/tasks.py
berk.egg-info/PKG-INFO
berk.egg-info/SOURCES.txt
berk.egg-info/dependency_links.txt
berk.egg-info/top_level.txt
bin/berk
bin/berk_chain
bin/mkat_primary_beam_correct
docs/Makefile
docs/commands.rst
docs/conf.py
docs/index.rst
docs/install.rst
docs/usage.rst